Workbook

Sheet Inputs
A1: Retirement Planner – Inputs
A3: Current Age (You) | B3: 43
A4: Life Expectancy | B4: 80
A5: Retirement Age | B5: 43
A6: Current Corpus (₹) | B6: 15000000
A7: Annual Household Expense Today (₹) | B7: 600000 | D7: =B7/12 -> 50000
A8: Household Expense Inflation (annual) | B8: 0.07
A9: Pre-Retirement Return (annual) | B9: 0.1
A10: Post-Retirement Return (annual) | B10: 0.1
A11: Son Age Now | B11: 13
A12: Daughter Age Now | B12: 4
A13: Son School Fee Today (₹) | B13: 200000
A14: Daughter School Fee Today (₹) | B14: 100000
A15: School Fee Hike (step every 2 yrs) | B15: 0.25
A16: Graduation Total Today (4 yrs) (₹) | B16: 1200000
A17: Graduation Inflation (annual) | B17: 0.07
A18: Marriage Cost Today (₹) | B18: 500000
A19: Marriage Inflation (annual) | B19: 0.07
... A23: Base Year | B23: 2026

Sheet Projection
A1: Year | B1: Your Age | C1: Corpus Start (₹) | D1: Household Expense (₹) | E1: Son Age | F1: Daughter Age | G1: Son School Fee (₹) | H1: Daughter School Fee (₹) | I1: Total School Fees (₹) | J1: Son Graduation (₹) | K1: Daughter Graduation (₹) | L1: Total Graduation (₹) | M1: Son Marriage (₹) | N1: Daughter Marriage (₹) | O1: Total Marriage (₹) | P1: Total Withdrawals (₹) | Q1: Investment Return (₹) | R1: Corpus End (₹)
A2: =Inputs!B23 + ROW()-2 -> 2026 | B2: =Inputs!B3 + ROW()-2 -> 43 | C2: =IF(ROW()=2,Inputs!B6,R1) -> 15000000 | D2: =IF(B2<Inputs!B5,0, Inputs!B7*(1+Inputs!B8)^(B2-Inputs!B3)) -> 600000 | E2: =Inputs!B11 + (B2-Inputs!B3) -> 13 | F2: =Inputs!B12 + (B2-Inputs!B3) -> 4 | G2: =IF(E2<18, Inputs!B13*(1+Inputs!B15)^(INT((B2-Inputs!B3)/Inputs!B22)), 0) -> 200000 | H2: =IF(F2<18, Inputs!B14*(1+Inputs!B15)^(INT((B2-Inputs!B3)/Inputs!B22)), 0) -> 100000 | I2: =G2+H2 -> 300000 | J2: =IF(AND(E2>=18,E2<=21), (Inputs!B16*(1+Inputs!B17)^(18-Inputs!B11))/4, 0) -> 0 | K2: =IF(AND(F2>=18,F2<=21), (Inputs!B16*(1+Inputs!B17)^(18-Inputs!B12))/4, 0) -> 0 | L2: =J2+K2 -> 0 | M2: =IF(E2=Inputs!B20, Inputs!B18*(1+Inputs!B19)^(Inputs!B20-Inputs!B11), 0) -> 0 | N2: =IF(F2=Inputs!B21, Inputs!B18*(1+Inputs!B19)^(Inputs!B21-Inputs!B12), 0) -> 0 | O2: =M2+N2 -> 0 | P2: =D2+I2+L2+O2 -> 900000 | Q2: =(C2-P2)*IF(B2<Inputs!B5,Inputs!B9,Inputs!B10) -> 1410000 | R2: =(C2-P2)+Q2 -> 15510000
A3: =Inputs!B23 + ROW()-2 -> 2027 | B3: =Inputs!B3 + ROW()-2 -> 44 | C3: =IF(ROW()=2,Inputs!B6,R2) -> 15510000 | D3: =IF(B3<Inputs!B5,0, Inputs!B7*(1+Inputs!B8)^(B3-Inputs!B3)) -> 642000 | E3: =Inputs!B11 + (B3-Inputs!B3) -> 14 | F3: =Inputs!B12 + (B3-Inputs!B3) -> 5 | G3: =IF(E3<18, Inputs!B13*(1+Inputs!B15)^(INT((B3-Inputs!B3)/Inputs!B22)), 0) -> 200000 | H3: =IF(F3<18, Inputs!B14*(1+Inputs!B15)^(INT((B3-Inputs!B3)/Inputs!B22)), 0) -> 100000 | I3: =G3+H3 -> 300000 | J3: =IF(AND(E3>=18,E3<=21), (Inputs!B16*(1+Inputs!B17)^(18-Inputs!B11))/4, 0) -> 0 | K3: =IF(AND(F3>=18,F3<=21), (Inputs!B16*(1+Inputs!B17)^(18-Inputs!B12))/4, 0) -> 0 | L3: =J3+K3 -> 0 | M3: =IF(E3=Inputs!B20, Inputs!B18*(1+Inputs!B19)^(Inputs!B20-Inputs!B11), 0) -> 0 | N3: =IF(F3=Inputs!B21, Inputs!B18*(1+Inputs!B19)^(Inputs!B21-Inputs!B12), 0) -> 0 | O3: =M3+N3 -> 0 | P3: =D3+I3+L3+O3 -> 942000 | Q3: =(C3-P3)*IF(B3<Inputs!B5,Inputs!B9,Inputs!B10) -> 1456800 | R3: =(C3-P3)+Q3 -> 16024800
A4: =Inputs!B23 + ROW()-2 -> 2028 | B4: =Inputs!B3 + ROW()-2 -> 45 | C4: =IF(ROW()=2,Inputs!B6,R3) -> 16024800 | D4: =IF(B4<Inputs!B5,0, Inputs!B7*(1+Inputs!B8)^(B4-Inputs!B3)) -> 686940 | E4: =Inputs!B11 + (B4-Inputs!B3) -> 15 | F4: =Inputs!B12 + (B4-Inputs!B3) -> 6 | G4: =IF(E4<18, Inputs!B13*(1+Inputs!B15)^(INT((B4-Inputs!B3)/Inputs!B22)), 0) -> 250000 | H4: =IF(F4<18, Inputs!B14*(1+Inputs!B15)^(INT((B4-Inputs!B3)/Inputs!B22)), 0) -> 125000 | I4: =G4+H4 -> 375000 | J4: =IF(AND(E4>=18,E4<=21), (Inputs!B16*(1+Inputs!B17)^(18-Inputs!B11))/4, 0) -> 0 | K4: =IF(AND(F4>=18,F4<=21), (Inputs!B16*(1+Inputs!B17)^(18-Inputs!B12))/4, 0) -> 0 | L4: =J4+K4 -> 0 | M4: =IF(E4=Inputs!B20, Inputs!B18*(1+Inputs!B19)^(Inputs!B20-Inputs!B11), 0) -> 0 | N4: =IF(F4=Inputs!B21, Inputs!B18*(1+Inputs!B19)^(Inputs!B21-Inputs!B12), 0) -> 0 | O4: =M4+N4 -> 0 | P4: =D4+I4+L4+O4 -> 1061940 | Q4: =(C4-P4)*IF(B4<Inputs!B5,Inputs!B9,Inputs!B10) -> 1496286 | R4: =(C4-P4)+Q4 -> 16459146
A5: =Inputs!B23 + ROW()-2 -> 2029 | B5: =Inputs!B3 + ROW()-2 -> 46 | C5: =IF(ROW()=2,Inputs!B6,R4) -> 16459146 | D5: =IF(B5<Inputs!B5,0, Inputs!B7*(1+Inputs!B8)^(B5-Inputs!B3)) -> 735025.8 | E5: =Inputs!B11 + (B5-Inputs!B3) -> 16 | F5: =Inputs!B12 + (B5-Inputs!B3) -> 7 | G5: =IF(E5<18, Inputs!B13*(1+Inputs!B15)^(INT((B5-Inputs!B3)/Inputs!B22)), 0) -> 250000 | H5: =IF(F5<18, Inputs!B14*(1+Inputs!B15)^(INT((B5-Inputs!B3)/Inputs!B22)), 0) -> 125000 | I5: =G5+H5 -> 375000 | J5: =IF(AND(E5>=18,E5<=21), (Inputs!B16*(1+Inputs!B17)^(18-Inputs!B11))/4, 0) -> 0 | K5: =IF(AND(F5>=18,F5<=21), (Inputs!B16*(1+Inputs!B17)^(18-Inputs!B12))/4, 0) -> 0 | L5: =J5+K5 -> 0 | M5: =IF(E5=Inputs!B20, Inputs!B18*(1+Inputs!B19)^(Inputs!B20-Inputs!B11), 0) -> 0 | N5: =IF(F5=Inputs!B21, Inputs!B18*(1+Inputs!B19)^(Inputs!B21-Inputs!B12), 0) -> 0 | O5: =M5+N5 -> 0 | P5: =D5+I5+L5+O5 -> 1110025.8 | Q5: =(C5-P5)*IF(B5<Inputs!B5,Inputs!B9,Inputs!B10) -> 1534912 | R5: =(C5-P5)+Q5 -> 16884032
A6: =Inputs!B23 + ROW()-2 -> 2030 | B6: =Inputs!B3 + ROW()-2 -> 47 | C6: =IF(ROW()=2,Inputs!B6,R5) -> 16884032 | D6: =IF(B6<Inputs!B5,0, Inputs!B7*(1+Inputs!B8)^(B6-Inputs!B3)) -> 786477.61 | E6: =Inputs!B11 + (B6-Inputs!B3) -> 17 | F6: =Inputs!B12 + (B6-Inputs!B3) -> 8 | G6: =IF(E6<18, Inputs!B13*(1+Inputs!B15)^(INT((B6-Inputs!B3)/Inputs!B22)), 0) -> 312500 | H6: =IF(F6<18, Inputs!B14*(1+Inputs!B15)^(INT((B6-Inputs!B3)/Inputs!B22)), 0) -> 156250 | I6: =G6+H6 -> 468750 | J6: =IF(AND(E6>=18,E6<=21), (Inputs!B16*(1+Inputs!B17)^(18-Inputs!B11))/4, 0) -> 0 | K6: =IF(AND(F6>=18,F6<=21), (Inputs!B16*(1+Inputs!B17)^(18-Inputs!B12))/4, 0) -> 0 | L6: =J6+K6 -> 0 | M6: =IF(E6=Inputs!B20, Inputs!B18*(1+Inputs!B19)^(Inputs!B20-Inputs!B11), 0) -> 0 | N6: =IF(F6=Inputs!B21, Inputs!B18*(1+Inputs!B19)^(Inputs!B21-Inputs!B12), 0) -> 0 | O6: =M6+N6 -> 0 | P6: =D6+I6+L6+O6 -> 1255227.6 | Q6: =(C6-P6)*IF(B6<Inputs!B5,Inputs!B9,Inputs!B10) -> 1562880.5 | R6: =(C6-P6)+Q6 -> 17191685
A7: =Inputs!B23 + ROW()-2 -> 2031 | B7: =Inputs!B3 + ROW()-2 -> 48 | C7: =IF(ROW()=2,Inputs!B6,R6) -> 17191685 | D7: =IF(B7<Inputs!B5,0, Inputs!B7*(1+Inputs!B8)^(B7-Inputs!B3)) -> 841531.04 | E7: =Inputs!B11 + (B7-Inputs!B3) -> 18 | F7: =Inputs!B12 + (B7-Inputs!B3) -> 9 | G7: =IF(E7<18, Inputs!B13*(1+Inputs!B15)^(INT((B7-Inputs!B3)/Inputs!B22)), 0) -> 0 | H7: =IF(F7<18, Inputs!B14*(1+Inputs!B15)^(INT((B7-Inputs!B3)/Inputs!B22)), 0) -> 156250 | I7: =G7+H7 -> 156250 | J7: =IF(AND(E7>=18,E7<=21), (Inputs!B16*(1+Inputs!B17)^(18-Inputs!B11))/4, 0) -> 420765.52 | K7: =IF(AND(F7>=18,F7<=21), (Inputs!B16*(1+Inputs!B17)^(18-Inputs!B12))/4, 0) -> 0 | L7: =J7+K7 -> 420765.52 | M7: =IF(E7=Inputs!B20, Inputs!B18*(1+Inputs!B19)^(Inputs!B20-Inputs!B11), 0) -> 0 | N7: =IF(F7=Inputs!B21, Inputs!B18*(1+Inputs!B19)^(Inputs!B21-Inputs!B12), 0) -> 0 | O7: =M7+N7 -> 0 | P7: =D7+I7+L7+O7 -> 1418546.6 | Q7: =(C7-P7)*IF(B7<Inputs!B5,Inputs!B9,Inputs!B10) -> 1577313.9 | R7: =(C7-P7)+Q7 -> 17350452
A8: =Inputs!B23 + ROW()-2 -> 2032 | B8: =Inputs!B3 + ROW()-2 -> 49 | C8: =IF(ROW()=2,Inputs!B6,R7) -> 17350452 | D8: =IF(B8<Inputs!B5,0, Inputs!B7*(1+Inputs!B8)^(B8-Inputs!B3)) -> 900438.21 | E8: =Inputs!B11 + (B8-Inputs!B3) -> 19 | F8: =Inputs!B12 + (B8-Inputs!B3) -> 10 | G8: =IF(E8<18, Inputs!B13*(1+Inputs!B15)^(INT((B8-Inputs!B3)/Inputs!B22)), 0) -> 0 | H8: =IF(F8<18, Inputs!B14*(1+Inputs!B15)^(INT((B8-Inputs!B3)/Inputs!B22)), 0) -> 195312.5 | I8: =G8+H8 -> 195312.5 | J8: =IF(AND(E8>=18,E8<=21), (Inputs!B16*(1+Inputs!B17)^(18-Inputs!B11))/4, 0) -> 420765.52 | K8: =IF(AND(F8>=18,F8<=21), (Inputs!B16*(1+Inputs!B17)^(18-Inputs!B12))/4, 0) -> 0 | L8: =J8+K8 -> 420765.52 | M8: =IF(E8=Inputs!B20, Inputs!B18*(1+Inputs!B19)^(Inputs!B20-Inputs!B11), 0) -> 0 | N8: =IF(F8=Inputs!B21, Inputs!B18*(1+Inputs!B19)^(Inputs!B21-Inputs!B12), 0) -> 0 | O8: =M8+N8 -> 0 | P8: =D8+I8+L8+O8 -> 1516516.2 | Q8: =(C8-P8)*IF(B8<Inputs!B5,Inputs!B9,Inputs!B10) -> 1583393.6 | R8: =(C8-P8)+Q8 -> 17417330
A9: =Inputs!B23 + ROW()-2 -> 2033 | B9: =Inputs!B3 + ROW()-2 -> 50 | C9: =IF(ROW()=2,Inputs!B6,R8) -> 17417330 | D9: =IF(B9<Inputs!B5,0, Inputs!B7*(1+Inputs!B8)^(B9-Inputs!B3)) -> 963468.89 | E9: =Inputs!B11 + (B9-Inputs!B3) -> 20 | F9: =Inputs!B12 + (B9-Inputs!B3) -> 11 | G9: =IF(E9<18, Inputs!B13*(1+Inputs!B15)^(INT((B9-Inputs!B3)/Inputs!B22)), 0) -> 0 | H9: =IF(F9<18, Inputs!B14*(1+Inputs!B15)^(INT((B9-Inputs!B3)/Inputs!B22)), 0) -> 195312.5 | I9: =G9+H9 -> 195312.5 | J9: =IF(AND(E9>=18,E9<=21), (Inputs!B16*(1+Inputs!B17)^(18-Inputs!B11))/4, 0) -> 420765.52 | K9: =IF(AND(F9>=18,F9<=21), (Inputs!B16*(1+Inputs!B17)^(18-Inputs!B12))/4, 0) -> 0 | L9: =J9+K9 -> 420765.52 | M9: =IF(E9=Inputs!B20, Inputs!B18*(1+Inputs!B19)^(Inputs!B20-Inputs!B11), 0) -> 0 | N9: =IF(F9=Inputs!B21, Inputs!B18*(1+Inputs!B19)^(Inputs!B21-Inputs!B12), 0) -> 0 | O9: =M9+N9 -> 0 | P9: =D9+I9+L9+O9 -> 1579546.9 | Q9: =(C9-P9)*IF(B9<Inputs!B5,Inputs!B9,Inputs!B10) -> 1583778.3 | R9: =(C9-P9)+Q9 -> 17421561
A10: =Inputs!B23 + ROW()-2 -> 2034 | B10: =Inputs!B3 + ROW()-2 -> 51 | C10: =IF(ROW()=2,Inputs!B6,R9) -> 17421561 | D10: =IF(B10<Inputs!B5,0, Inputs!B7*(1+Inputs!B8)^(B10-Inputs!B3)) -> 1030911.7 | E10: =Inputs!B11 + (B10-Inputs!B3) -> 21 | F10: =Inputs!B12 + (B10-Inputs!B3) -> 12 | G10: =IF(E10<18, Inputs!B13*(1+Inputs!B15)^(INT((B10-Inputs!B3)/Inputs!B22)), 0) -> 0 | H10: =IF(F10<18, Inputs!B14*(1+Inputs!B15)^(INT((B10-Inputs!B3)/Inputs!B22)), 0) -> 244140.62 | I10: =G10+H10 -> 244140.62 | J10: =IF(AND(E10>=18,E10<=21), (Inputs!B16*(1+Inputs!B17)^(18-Inputs!B11))/4, 0) -> 420765.52 | K10: =IF(AND(F10>=18,F10<=21), (Inputs!B16*(1+Inputs!B17)^(18-Inputs!B12))/4, 0) -> 0 | L10: =J10+K10 -> 420765.52 | M10: =IF(E10=Inputs!B20, Inputs!B18*(1+Inputs!B19)^(Inputs!B20-Inputs!B11), 0) -> 0 | N10: =IF(F10=Inputs!B21, Inputs!B18*(1+Inputs!B19)^(Inputs!B21-Inputs!B12), 0) -> 0 | O10: =M10+N10 -> 0 | P10: =D10+I10+L10+O10 -> 1695817.9 | Q10: =(C10-P10)*IF(B10<Inputs!B5,Inputs!B9,Inputs!B10) -> 1572574.3 | R10: =(C10-P10)+Q10 -> 17298318
A11: =Inputs!B23 + ROW()-2 -> 2035 | B11: =Inputs!B3 + ROW()-2 -> 52 | C11: =IF(ROW()=2,Inputs!B6,R10) -> 17298318 | D11: =IF(B11<Inputs!B5,0, Inputs!B7*(1+Inputs!B8)^(B11-Inputs!B3)) -> 1103075.5 | E11: =Inputs!B11 + (B11-Inputs!B3) -> 22 | F11: =Inputs!B12 + (B11-Inputs!B3) -> 13 | G11: =IF(E11<18, Inputs!B13*(1+Inputs!B15)^(INT((B11-Inputs!B3)/Inputs!B22)), 0) -> 0 | H11: =IF(F11<18, Inputs!B14*(1+Inputs!B15)^(INT((B11-Inputs!B3)/Inputs!B22)), 0) -> 244140.62 | I11: =G11+H11 -> 244140.62 | J11: =IF(AND(E11>=18,E11<=21), (Inputs!B16*(1+Inputs!B17)^(18-Inputs!B11))/4, 0) -> 0 | K11: =IF(AND(F11>=18,F11<=21), (Inputs!B16*(1+Inputs!B17)^(18-Inputs!B12))/4, 0) -> 0 | L11: =J11+K11 -> 0 | M11: =IF(E11=Inputs!B20, Inputs!B18*(1+Inputs!B19)^(Inputs!B20-Inputs!B11), 0) -> 0 | N11: =IF(F11=Inputs!B21, Inputs!B18*(1+Inputs!B19)^(Inputs!B21-Inputs!B12), 0) -> 0 | O11: =M11+N11 -> 0 | P11: =D11+I11+L11+O11 -> 1347216.2 | Q11: =(C11-P11)*IF(B11<Inputs!B5,Inputs!B9,Inputs!B10) -> 1595110.1 | R11: =(C11-P11)+Q11 -> 17546212
A12: =Inputs!B23 + ROW()-2 -> 2036 | B12: =Inputs!B3 + ROW()-2 -> 53 | C12: =IF(ROW()=2,Inputs!B6,R11) -> 17546212 | D12: =IF(B12<Inputs!B5,0, Inputs!B7*(1+Inputs!B8)^(B12-Inputs!B3)) -> 1180290.8 | E12: =Inputs!B11 + (B12-Inputs!B3) -> 23 | F12: =Inputs!B12 + (B12-Inputs!B3) -> 14 | G12: =IF(E12<18, Inputs!B13*(1+Inputs!B15)^(INT((B12-Inputs!B3)/Inputs!B22)), 0) -> 0 | H12: =IF(F12<18, Inputs!B14*(1+Inputs!B15)^(INT((B12-Inputs!B3)/Inputs!B22)), 0) -> 305175.78 | I12: =G12+H12 -> 305175.78 | J12: =IF(AND(E12>=18,E12<=21), (Inputs!B16*(1+Inputs!B17)^(18-Inputs!B11))/4, 0) -> 0 | K12: =IF(AND(F12>=18,F12<=21), (Inputs!B16*(1+Inputs!B17)^(18-Inputs!B12))/4, 0) -> 0 | L12: =J12+K12 -> 0 | M12: =IF(E12=Inputs!B20, Inputs!B18*(1+Inputs!B19)^(Inputs!B20-Inputs!B11), 0) -> 0 | N12: =IF(F12=Inputs!B21, Inputs!B18*(1+Inputs!B19)^(Inputs!B21-Inputs!B12), 0) -> 0 | O12: =M12+N12 -> 0 | P12: =D12+I12+L12+O12 -> 1485466.6 | Q12: =(C12-P12)*IF(B12<Inputs!B5,Inputs!B9,Inputs!B10) -> 1606074.5 | R12: =(C12-P12)+Q12 -> 17666820
A13: =Inputs!B23 + ROW()-2 -> 2037 | B13: =Inputs!B3 + ROW()-2 -> 54 | C13: =IF(ROW()=2,Inputs!B6,R12) -> 17666820 | D13: =IF(B13<Inputs!B5,0, Inputs!B7*(1+Inputs!B8)^(B13-Inputs!B3)) -> 1262911.2 | E13: =Inputs!B11 + (B13-Inputs!B3) -> 24 | F13: =Inputs!B12 + (B13-Inputs!B3) -> 15 | G13: =IF(E13<18, Inputs!B13*(1+Inputs!B15)^(INT((B13-Inputs!B3)/Inputs!B22)), 0) -> 0 | H13: =IF(F13<18, Inputs!B14*(1+Inputs!B15)^(INT((B13-Inputs!B3)/Inputs!B22)), 0) -> 305175.78 | I13: =G13+H13 -> 305175.78 | J13: =IF(AND(E13>=18,E13<=21), (Inputs!B16*(1+Inputs!B17)^(18-Inputs!B11))/4, 0) -> 0 | K13: =IF(AND(F13>=18,F13<=21), (Inputs!B16*(1+Inputs!B17)^(18-Inputs!B12))/4, 0) -> 0 | L13: =J13+K13 -> 0 | M13: =IF(E13=Inputs!B20, Inputs!B18*(1+Inputs!B19)^(Inputs!B20-Inputs!B11), 0) -> 0 | N13: =IF(F13=Inputs!B21, Inputs!B18*(1+Inputs!B19)^(Inputs!B21-Inputs!B12), 0) -> 0 | O13: =M13+N13 -> 0 | P13: =D13+I13+L13+O13 -> 1568087 | Q13: =(C13-P13)*IF(B13<Inputs!B5,Inputs!B9,Inputs!B10) -> 1609873.3 | R13: =(C13-P13)+Q13 -> 17708606
A14: =Inputs!B23 + ROW()-2 -> 2038 | B14: =Inputs!B3 + ROW()-2 -> 55 | C14: =IF(ROW()=2,Inputs!B6,R13) -> 17708606 | D14: =IF(B14<Inputs!B5,0, Inputs!B7*(1+Inputs!B8)^(B14-Inputs!B3)) -> 1351315 | E14: =Inputs!B11 + (B14-Inputs!B3) -> 25 | F14: =Inputs!B12 + (B14-Inputs!B3) -> 16 | G14: =IF(E14<18, Inputs!B13*(1+Inputs!B15)^(INT((B14-Inputs!B3)/Inputs!B22)), 0) -> 0 | H14: =IF(F14<18, Inputs!B14*(1+Inputs!B15)^(INT((B14-Inputs!B3)/Inputs!B22)), 0) -> 381469.73 | I14: =G14+H14 -> 381469.73 | J14: =IF(AND(E14>=18,E14<=21), (Inputs!B16*(1+Inputs!B17)^(18-Inputs!B11))/4, 0) -> 0 | K14: =IF(AND(F14>=18,F14<=21), (Inputs!B16*(1+Inputs!B17)^(18-Inputs!B12))/4, 0) -> 0 | L14: =J14+K14 -> 0 | M14: =IF(E14=Inputs!B20, Inputs!B18*(1+Inputs!B19)^(Inputs!B20-Inputs!B11), 0) -> 0 | N14: =IF(F14=Inputs!B21, Inputs!B18*(1+Inputs!B19)^(Inputs!B21-Inputs!B12), 0) -> 0 | O14: =M14+N14 -> 0 | P14: =D14+I14+L14+O14 -> 1732784.7 | Q14: =(C14-P14)*IF(B14<Inputs!B5,Inputs!B9,Inputs!B10) -> 1597582.1 | R14: =(C14-P14)+Q14 -> 17573403
A15: =Inputs!B23 + ROW()-2 -> 2039 | B15: =Inputs!B3 + ROW()-2 -> 56 | C15: =IF(ROW()=2,Inputs!B6,R14) -> 17573403 | D15: =IF(B15<Inputs!B5,0, Inputs!B7*(1+Inputs!B8)^(B15-Inputs!B3)) -> 1445907 | E15: =Inputs!B11 + (B15-Inputs!B3) -> 26 | F15: =Inputs!B12 + (B15-Inputs!B3) -> 17 | G15: =IF(E15<18, Inputs!B13*(1+Inputs!B15)^(INT((B15-Inputs!B3)/Inputs!B22)), 0) -> 0 | H15: =IF(F15<18, Inputs!B14*(1+Inputs!B15)^(INT((B15-Inputs!B3)/Inputs!B22)), 0) -> 381469.73 | I15: =G15+H15 -> 381469.73 | J15: =IF(AND(E15>=18,E15<=21), (Inputs!B16*(1+Inputs!B17)^(18-Inputs!B11))/4, 0) -> 0 | K15: =IF(AND(F15>=18,F15<=21), (Inputs!B16*(1+Inputs!B17)^(18-Inputs!B12))/4, 0) -> 0 | L15: =J15+K15 -> 0 | M15: =IF(E15=Inputs!B20, Inputs!B18*(1+Inputs!B19)^(Inputs!B20-Inputs!B11), 0) -> 0 | N15: =IF(F15=Inputs!B21, Inputs!B18*(1+Inputs!B19)^(Inputs!B21-Inputs!B12), 0) -> 0 | O15: =M15+N15 -> 0 | P15: =D15+I15+L15+O15 -> 1827376.7 | Q15: =(C15-P15)*IF(B15<Inputs!B5,Inputs!B9,Inputs!B10) -> 1574602.7 | R15: =(C15-P15)+Q15 -> 17320629
A16: =Inputs!B23 + ROW()-2 -> 2040 | B16: =Inputs!B3 + ROW()-2 -> 57 | C16: =IF(ROW()=2,Inputs!B6,R15) -> 17320629 | D16: =IF(B16<Inputs!B5,0, Inputs!B7*(1+Inputs!B8)^(B16-Inputs!B3)) -> 1547120.5 | E16: =Inputs!B11 + (B16-Inputs!B3) -> 27 | F16: =Inputs!B12 + (B16-Inputs!B3) -> 18 | G16: =IF(E16<18, Inputs!B13*(1+Inputs!B15)^(INT((B16-Inputs!B3)/Inputs!B22)), 0) -> 0 | H16: =IF(F16<18, Inputs!B14*(1+Inputs!B15)^(INT((B16-Inputs!B3)/Inputs!B22)), 0) -> 0 | I16: =G16+H16 -> 0 | J16: =IF(AND(E16>=18,E16<=21), (Inputs!B16*(1+Inputs!B17)^(18-Inputs!B11))/4, 0) -> 0 | K16: =IF(AND(F16>=18,F16<=21), (Inputs!B16*(1+Inputs!B17)^(18-Inputs!B12))/4, 0) -> 773560.25 | L16: =J16+K16 -> 773560.25 | M16: =IF(E16=Inputs!B20, Inputs!B18*(1+Inputs!B19)^(Inputs!B20-Inputs!B11), 0) -> 0 | N16: =IF(F16=Inputs!B21, Inputs!B18*(1+Inputs!B19)^(Inputs!B21-Inputs!B12), 0) -> 0 | O16: =M16+N16 -> 0 | P16: =D16+I16+L16+O16 -> 2320680.7 | Q16: =(C16-P16)*IF(B16<Inputs!B5,Inputs!B9,Inputs!B10) -> 1499994.8 | R16: =(C16-P16)+Q16 -> 16499943
A17: =Inputs!B23 + ROW()-2 -> 2041 | B17: =Inputs!B3 + ROW()-2 -> 58 | C17: =IF(ROW()=2,Inputs!B6,R16) -> 16499943 | D17: =IF(B17<Inputs!B5,0, Inputs!B7*(1+Inputs!B8)^(B17-Inputs!B3)) -> 1655418.9 | E17: =Inputs!B11 + (B17-Inputs!B3) -> 28 | F17: =Inputs!B12 + (B17-Inputs!B3) -> 19 | G17: =IF(E17<18, Inputs!B13*(1+Inputs!B15)^(INT((B17-Inputs!B3)/Inputs!B22)), 0) -> 0 | H17: =IF(F17<18, Inputs!B14*(1+Inputs!B15)^(INT((B17-Inputs!B3)/Inputs!B22)), 0) -> 0 | I17: =G17+H17 -> 0 | J17: =IF(AND(E17>=18,E17<=21), (Inputs!B16*(1+Inputs!B17)^(18-Inputs!B11))/4, 0) -> 0 | K17: =IF(AND(F17>=18,F17<=21), (Inputs!B16*(1+Inputs!B17)^(18-Inputs!B12))/4, 0) -> 773560.25 | L17: =J17+K17 -> 773560.25 | M17: =IF(E17=Inputs!B20, Inputs!B18*(1+Inputs!B19)^(Inputs!B20-Inputs!B11), 0) -> 1379515.8 | N17: =IF(F17=Inputs!B21, Inputs!B18*(1+Inputs!B19)^(Inputs!B21-Inputs!B12), 0) -> 0 | O17: =M17+N17 -> 1379515.8 | P17: =D17+I17+L17+O17 -> 3808494.9 | Q17: =(C17-P17)*IF(B17<Inputs!B5,Inputs!B9,Inputs!B10) -> 1269144.8 | R17: =(C17-P17)+Q17 -> 13960593
A18: =Inputs!B23 + ROW()-2 -> 2042 | B18: =Inputs!B3 + ROW()-2 -> 59 | C18: =IF(ROW()=2,Inputs!B6,R17) -> 13960593 | D18: =IF(B18<Inputs!B5,0, Inputs!B7*(1+Inputs!B8)^(B18-Inputs!B3)) -> 1771298.2 | E18: =Inputs!B11 + (B18-Inputs!B3) -> 29 | F18: =Inputs!B12 + (B18-Inputs!B3) -> 20 | G18: =IF(E18<18, Inputs!B13*(1+Inputs!B15)^(INT((B18-Inputs!B3)/Inputs!B22)), 0) -> 0 | H18: =IF(F18<18, Inputs!B14*(1+Inputs!B15)^(INT((B18-Inputs!B3)/Inputs!B22)), 0) -> 0 | I18: =G18+H18 -> 0 | J18: =IF(AND(E18>=18,E18<=21), (Inputs!B16*(1+Inputs!B17)^(18-Inputs!B11))/4, 0) -> 0 | K18: =IF(AND(F18>=18,F18<=21), (Inputs!B16*(1+Inputs!B17)^(18-Inputs!B12))/4, 0) -> 773560.25 | L18: =J18+K18 -> 773560.25 | M18: =IF(E18=Inputs!B20, Inputs!B18*(1+Inputs!B19)^(Inputs!B20-Inputs!B11), 0) -> 0 | N18: =IF(F18=Inputs!B21, Inputs!B18*(1+Inputs!B19)^(Inputs!B21-Inputs!B12), 0) -> 0 | O18: =M18+N18 -> 0 | P18: =D18+I18+L18+O18 -> 2544858.5 | Q18: =(C18-P18)*IF(B18<Inputs!B5,Inputs!B9,Inputs!B10) -> 1141573.5 | R18: =(C18-P18)+Q18 -> 12557308
A19: =Inputs!B23 + ROW()-2 -> 2043 | B19: =Inputs!B3 + ROW()-2 -> 60 | C19: =IF(ROW()=2,Inputs!B6,R18) -> 12557308 | D19: =IF(B19<Inputs!B5,0, Inputs!B7*(1+Inputs!B8)^(B19-Inputs!B3)) -> 1895289.1 | E19: =Inputs!B11 + (B19-Inputs!B3) -> 30 | F19: =Inputs!B12 + (B19-Inputs!B3) -> 21 | G19: =IF(E19<18, Inputs!B13*(1+Inputs!B15)^(INT((B19-Inputs!B3)/Inputs!B22)), 0) -> 0 | H19: =IF(F19<18, Inputs!B14*(1+Inputs!B15)^(INT((B19-Inputs!B3)/Inputs!B22)), 0) -> 0 | I19: =G19+H19 -> 0 | J19: =IF(AND(E19>=18,E19<=21), (Inputs!B16*(1+Inputs!B17)^(18-Inputs!B11))/4, 0) -> 0 | K19: =IF(AND(F19>=18,F19<=21), (Inputs!B16*(1+Inputs!B17)^(18-Inputs!B12))/4, 0) -> 773560.25 | L19: =J19+K19 -> 773560.25 | M19: =IF(E19=Inputs!B20, Inputs!B18*(1+Inputs!B19)^(Inputs!B20-Inputs!B11), 0) -> 0 | N19: =IF(F19=Inputs!B21, Inputs!B18*(1+Inputs!B19)^(Inputs!B21-Inputs!B12), 0) -> 0 | O19: =M19+N19 -> 0 | P19: =D19+I19+L19+O19 -> 2668849.4 | Q19: =(C19-P19)*IF(B19<Inputs!B5,Inputs!B9,Inputs!B10) -> 988845.88 | R19: =(C19-P19)+Q19 -> 10877305
A20: =Inputs!B23 + ROW()-2 -> 2044 | B20: =Inputs!B3 + ROW()-2 -> 61 | C20: =IF(ROW()=2,Inputs!B6,R19) -> 10877305 | D20: =IF(B20<Inputs!B5,0, Inputs!B7*(1+Inputs!B8)^(B20-Inputs!B3)) -> 2027959.4 | E20: =Inputs!B11 + (B20-Inputs!B3) -> 31 | F20: =Inputs!B12 + (B20-Inputs!B3) -> 22 | G20: =IF(E20<18, Inputs!B13*(1+Inputs!B15)^(INT((B20-Inputs!B3)/Inputs!B22)), 0) -> 0 | H20: =IF(F20<18, Inputs!B14*(1+Inputs!B15)^(INT((B20-Inputs!B3)/Inputs!B22)), 0) -> 0 | I20: =G20+H20 -> 0 | J20: =IF(AND(E20>=18,E20<=21), (Inputs!B16*(1+Inputs!B17)^(18-Inputs!B11))/4, 0) -> 0 | K20: =IF(AND(F20>=18,F20<=21), (Inputs!B16*(1+Inputs!B17)^(18-Inputs!B12))/4, 0) -> 0 | L20: =J20+K20 -> 0 | M20: =IF(E20=Inputs!B20, Inputs!B18*(1+Inputs!B19)^(Inputs!B20-Inputs!B11), 0) -> 0 | N20: =IF(F20=Inputs!B21, Inputs!B18*(1+Inputs!B19)^(Inputs!B21-Inputs!B12), 0) -> 0 | O20: =M20+N20 -> 0 | P20: =D20+I20+L20+O20 -> 2027959.4 | Q20: =(C20-P20)*IF(B20<Inputs!B5,Inputs!B9,Inputs!B10) -> 884934.53 | R20: =(C20-P20)+Q20 -> 9734279.8
A21: =Inputs!B23 + ROW()-2 -> 2045 | B21: =Inputs!B3 + ROW()-2 -> 62 | C21: =IF(ROW()=2,Inputs!B6,R20) -> 9734279.8 | D21: =IF(B21<Inputs!B5,0, Inputs!B7*(1+Inputs!B8)^(B21-Inputs!B3)) -> 2169916.5 | E21: =Inputs!B11 + (B21-Inputs!B3) -> 32 | F21: =Inputs!B12 + (B21-Inputs!B3) -> 23 | G21: =IF(E21<18, Inputs!B13*(1+Inputs!B15)^(INT((B21-Inputs!B3)/Inputs!B22)), 0) -> 0 | H21: =IF(F21<18, Inputs!B14*(1+Inputs!B15)^(INT((B21-Inputs!B3)/Inputs!B22)), 0) -> 0 | I21: =G21+H21 -> 0 | J21: =IF(AND(E21>=18,E21<=21), (Inputs!B16*(1+Inputs!B17)^(18-Inputs!B11))/4, 0) -> 0 | K21: =IF(AND(F21>=18,F21<=21), (Inputs!B16*(1+Inputs!B17)^(18-Inputs!B12))/4, 0) -> 0 | L21: =J21+K21 -> 0 | M21: =IF(E21=Inputs!B20, Inputs!B18*(1+Inputs!B19)^(Inputs!B20-Inputs!B11), 0) -> 0 | N21: =IF(F21=Inputs!B21, Inputs!B18*(1+Inputs!B19)^(Inputs!B21-Inputs!B12), 0) -> 0 | O21: =M21+N21 -> 0 | P21: =D21+I21+L21+O21 -> 2169916.5 | Q21: =(C21-P21)*IF(B21<Inputs!B5,Inputs!B9,Inputs!B10) -> 756436.33 | R21: =(C21-P21)+Q21 -> 8320799.6
A22: =Inputs!B23 + ROW()-2 -> 2046 | B22: =Inputs!B3 + ROW()-2 -> 63 | C22: =IF(ROW()=2,Inputs!B6,R21) -> 8320799.6 | D22: =IF(B22<Inputs!B5,0, Inputs!B7*(1+Inputs!B8)^(B22-Inputs!B3)) -> 2321810.7 | E22: =Inputs!B11 + (B22-Inputs!B3) -> 33 | F22: =Inputs!B12 + (B22-Inputs!B3) -> 24 | G22: =IF(E22<18, Inputs!B13*(1+Inputs!B15)^(INT((B22-Inputs!B3)/Inputs!B22)), 0) -> 0 | H22: =IF(F22<18, Inputs!B14*(1+Inputs!B15)^(INT((B22-Inputs!B3)/Inputs!B22)), 0) -> 0 | I22: =G22+H22 -> 0 | J22: =IF(AND(E22>=18,E22<=21), (Inputs!B16*(1+Inputs!B17)^(18-Inputs!B11))/4, 0) -> 0 | K22: =IF(AND(F22>=18,F22<=21), (Inputs!B16*(1+Inputs!B17)^(18-Inputs!B12))/4, 0) -> 0 | L22: =J22+K22 -> 0 | M22: =IF(E22=Inputs!B20, Inputs!B18*(1+Inputs!B19)^(Inputs!B20-Inputs!B11), 0) -> 0 | N22: =IF(F22=Inputs!B21, Inputs!B18*(1+Inputs!B19)^(Inputs!B21-Inputs!B12), 0) -> 0 | O22: =M22+N22 -> 0 | P22: =D22+I22+L22+O22 -> 2321810.7 | Q22: =(C22-P22)*IF(B22<Inputs!B5,Inputs!B9,Inputs!B10) -> 599898.89 | R22: =(C22-P22)+Q22 -> 6598887.8
A23: =Inputs!B23 + ROW()-2 -> 2047 | B23: =Inputs!B3 + ROW()-2 -> 64 | C23: =IF(ROW()=2,Inputs!B6,R22) -> 6598887.8 | D23: =IF(B23<Inputs!B5,0, Inputs!B7*(1+Inputs!B8)^(B23-Inputs!B3)) -> 2484337.4 | E23: =Inputs!B11 + (B23-Inputs!B3) -> 34 | F23: =Inputs!B12 + (B23-Inputs!B3) -> 25 | G23: =IF(E23<18, Inputs!B13*(1+Inputs!B15)^(INT((B23-Inputs!B3)/Inputs!B22)), 0) -> 0 | H23: =IF(F23<18, Inputs!B14*(1+Inputs!B15)^(INT((B23-Inputs!B3)/Inputs!B22)), 0) -> 0 | I23: =G23+H23 -> 0 | J23: =IF(AND(E23>=18,E23<=21), (Inputs!B16*(1+Inputs!B17)^(18-Inputs!B11))/4, 0) -> 0 | K23: =IF(AND(F23>=18,F23<=21), (Inputs!B16*(1+Inputs!B17)^(18-Inputs!B12))/4, 0) -> 0 | L23: =J23+K23 -> 0 | M23: =IF(E23=Inputs!B20, Inputs!B18*(1+Inputs!B19)^(Inputs!B20-Inputs!B11), 0) -> 0 | N23: =IF(F23=Inputs!B21, Inputs!B18*(1+Inputs!B19)^(Inputs!B21-Inputs!B12), 0) -> 2070281.2 | O23: =M23+N23 -> 2070281.2 | P23: =D23+I23+L23+O23 -> 4554618.6 | Q23: =(C23-P23)*IF(B23<Inputs!B5,Inputs!B9,Inputs!B10) -> 204426.92 | R23: =(C23-P23)+Q23 -> 2248696.1
A24: =Inputs!B23 + ROW()-2 -> 2048 | B24: =Inputs!B3 + ROW()-2 -> 65 | C24: =IF(ROW()=2,Inputs!B6,R23) -> 2248696.1 | D24: =IF(B24<Inputs!B5,0, Inputs!B7*(1+Inputs!B8)^(B24-Inputs!B3)) -> 2658241 | E24: =Inputs!B11 + (B24-Inputs!B3) -> 35 | F24: =Inputs!B12 + (B24-Inputs!B3) -> 26 | G24: =IF(E24<18, Inputs!B13*(1+Inputs!B15)^(INT((B24-Inputs!B3)/Inputs!B22)), 0) -> 0 | H24: =IF(F24<18, Inputs!B14*(1+Inputs!B15)^(INT((B24-Inputs!B3)/Inputs!B22)), 0) -> 0 | I24: =G24+H24 -> 0 | J24: =IF(AND(E24>=18,E24<=21), (Inputs!B16*(1+Inputs!B17)^(18-Inputs!B11))/4, 0) -> 0 | K24: =IF(AND(F24>=18,F24<=21), (Inputs!B16*(1+Inputs!B17)^(18-Inputs!B12))/4, 0) -> 0 | L24: =J24+K24 -> 0 | M24: =IF(E24=Inputs!B20, Inputs!B18*(1+Inputs!B19)^(Inputs!B20-Inputs!B11), 0) -> 0 | N24: =IF(F24=Inputs!B21, Inputs!B18*(1+Inputs!B19)^(Inputs!B21-Inputs!B12), 0) -> 0 | O24: =M24+N24 -> 0 | P24: =D24+I24+L24+O24 -> 2658241 | Q24: =(C24-P24)*IF(B24<Inputs!B5,Inputs!B9,Inputs!B10) -> -40954.49 | R24: =(C24-P24)+Q24 -> -450499.39
A25: =Inputs!B23 + ROW()-2 -> 2049 | B25: =Inputs!B3 + ROW()-2 -> 66 | C25: =IF(ROW()=2,Inputs!B6,R24) -> -450499.39 | D25: =IF(B25<Inputs!B5,0, Inputs!B7*(1+Inputs!B8)^(B25-Inputs!B3)) -> 2844317.9 | E25: =Inputs!B11 + (B25-Inputs!B3) -> 36 | F25: =Inputs!B12 + (B25-Inputs!B3) -> 27 | G25: =IF(E25<18, Inputs!B13*(1+Inputs!B15)^(INT((B25-Inputs!B3)/Inputs!B22)), 0) -> 0 | H25: =IF(F25<18, Inputs!B14*(1+Inputs!B15)^(INT((B25-Inputs!B3)/Inputs!B22)), 0) -> 0 | I25: =G25+H25 -> 0 | J25: =IF(AND(E25>=18,E25<=21), (Inputs!B16*(1+Inputs!B17)^(18-Inputs!B11))/4, 0) -> 0 | K25: =IF(AND(F25>=18,F25<=21), (Inputs!B16*(1+Inputs!B17)^(18-Inputs!B12))/4, 0) -> 0 | L25: =J25+K25 -> 0 | M25: =IF(E25=Inputs!B20, Inputs!B18*(1+Inputs!B19)^(Inputs!B20-Inputs!B11), 0) -> 0 | N25: =IF(F25=Inputs!B21, Inputs!B18*(1+Inputs!B19)^(Inputs!B21-Inputs!B12), 0) -> 0 | O25: =M25+N25 -> 0 | P25: =D25+I25+L25+O25 -> 2844317.9 | Q25: =(C25-P25)*IF(B25<Inputs!B5,Inputs!B9,Inputs!B10) -> -329481.73 | R25: =(C25-P25)+Q25 -> -3624299
A26: =Inputs!B23 + ROW()-2 -> 2050 | B26: =Inputs!B3 + ROW()-2 -> 67 | C26: =IF(ROW()=2,Inputs!B6,R25) -> -3624299 | D26: =IF(B26<Inputs!B5,0, Inputs!B7*(1+Inputs!B8)^(B26-Inputs!B3)) -> 3043420.2 | E26: =Inputs!B11 + (B26-Inputs!B3) -> 37 | F26: =Inputs!B12 + (B26-Inputs!B3) -> 28 | G26: =IF(E26<18, Inputs!B13*(1+Inputs!B15)^(INT((B26-Inputs!B3)/Inputs!B22)), 0) -> 0 | H26: =IF(F26<18, Inputs!B14*(1+Inputs!B15)^(INT((B26-Inputs!B3)/Inputs!B22)), 0) -> 0 | I26: =G26+H26 -> 0 | J26: =IF(AND(E26>=18,E26<=21), (Inputs!B16*(1+Inputs!B17)^(18-Inputs!B11))/4, 0) -> 0 | K26: =IF(AND(F26>=18,F26<=21), (Inputs!B16*(1+Inputs!B17)^(18-Inputs!B12))/4, 0) -> 0 | L26: =J26+K26 -> 0 | M26: =IF(E26=Inputs!B20, Inputs!B18*(1+Inputs!B19)^(Inputs!B20-Inputs!B11), 0) -> 0 | N26: =IF(F26=Inputs!B21, Inputs!B18*(1+Inputs!B19)^(Inputs!B21-Inputs!B12), 0) -> 0 | O26: =M26+N26 -> 0 | P26: =D26+I26+L26+O26 -> 3043420.2 | Q26: =(C26-P26)*IF(B26<Inputs!B5,Inputs!B9,Inputs!B10) -> -666771.92 | R26: =(C26-P26)+Q26 -> -7334491.1
A27: =Inputs!B23 + ROW()-2 -> 2051 | B27: =Inputs!B3 + ROW()-2 -> 68 | C27: =IF(ROW()=2,Inputs!B6,R26) -> -7334491.1 | D27: =IF(B27<Inputs!B5,0, Inputs!B7*(1+Inputs!B8)^(B27-Inputs!B3)) -> 3256459.6 | E27: =Inputs!B11 + (B27-Inputs!B3) -> 38 | F27: =Inputs!B12 + (B27-Inputs!B3) -> 29 | G27: =IF(E27<18, Inputs!B13*(1+Inputs!B15)^(INT((B27-Inputs!B3)/Inputs!B22)), 0) -> 0 | H27: =IF(F27<18, Inputs!B14*(1+Inputs!B15)^(INT((B27-Inputs!B3)/Inputs!B22)), 0) -> 0 | I27: =G27+H27 -> 0 | J27: =IF(AND(E27>=18,E27<=21), (Inputs!B16*(1+Inputs!B17)^(18-Inputs!B11))/4, 0) -> 0 | K27: =IF(AND(F27>=18,F27<=21), (Inputs!B16*(1+Inputs!B17)^(18-Inputs!B12))/4, 0) -> 0 | L27: =J27+K27 -> 0 | M27: =IF(E27=Inputs!B20, Inputs!B18*(1+Inputs!B19)^(Inputs!B20-Inputs!B11), 0) -> 0 | N27: =IF(F27=Inputs!B21, Inputs!B18*(1+Inputs!B19)^(Inputs!B21-Inputs!B12), 0) -> 0 | O27: =M27+N27 -> 0 | P27: =D27+I27+L27+O27 -> 3256459.6 | Q27: =(C27-P27)*IF(B27<Inputs!B5,Inputs!B9,Inputs!B10) -> -1059095.1 | R27: =(C27-P27)+Q27 -> -11650046
A28: =Inputs!B23 + ROW()-2 -> 2052 | B28: =Inputs!B3 + ROW()-2 -> 69 | C28: =IF(ROW()=2,Inputs!B6,R27) -> -11650046 | D28: =IF(B28<Inputs!B5,0, Inputs!B7*(1+Inputs!B8)^(B28-Inputs!B3)) -> 3484411.8 | E28: =Inputs!B11 + (B28-Inputs!B3) -> 39 | F28: =Inputs!B12 + (B28-Inputs!B3) -> 30 | G28: =IF(E28<18, Inputs!B13*(1+Inputs!B15)^(INT((B28-Inputs!B3)/Inputs!B22)), 0) -> 0 | H28: =IF(F28<18, Inputs!B14*(1+Inputs!B15)^(INT((B28-Inputs!B3)/Inputs!B22)), 0) -> 0 | I28: =G28+H28 -> 0 | J28: =IF(AND(E28>=18,E28<=21), (Inputs!B16*(1+Inputs!B17)^(18-Inputs!B11))/4, 0) -> 0 | K28: =IF(AND(F28>=18,F28<=21), (Inputs!B16*(1+Inputs!B17)^(18-Inputs!B12))/4, 0) -> 0 | L28: =J28+K28 -> 0 | M28: =IF(E28=Inputs!B20, Inputs!B18*(1+Inputs!B19)^(Inputs!B20-Inputs!B11), 0) -> 0 | N28: =IF(F28=Inputs!B21, Inputs!B18*(1+Inputs!B19)^(Inputs!B21-Inputs!B12), 0) -> 0 | O28: =M28+N28 -> 0 | P28: =D28+I28+L28+O28 -> 3484411.8 | Q28: =(C28-P28)*IF(B28<Inputs!B5,Inputs!B9,Inputs!B10) -> -1513445.8 | R28: =(C28-P28)+Q28 -> -16647903
A29: =Inputs!B23 + ROW()-2 -> 2053 | B29: =Inputs!B3 + ROW()-2 -> 70 | C29: =IF(ROW()=2,Inputs!B6,R28) -> -16647903 | D29: =IF(B29<Inputs!B5,0, Inputs!B7*(1+Inputs!B8)^(B29-Inputs!B3)) -> 3728320.6 | E29: =Inputs!B11 + (B29-Inputs!B3) -> 40 | F29: =Inputs!B12 + (B29-Inputs!B3) -> 31 | G29: =IF(E29<18, Inputs!B13*(1+Inputs!B15)^(INT((B29-Inputs!B3)/Inputs!B22)), 0) -> 0 | H29: =IF(F29<18, Inputs!B14*(1+Inputs!B15)^(INT((B29-Inputs!B3)/Inputs!B22)), 0) -> 0 | I29: =G29+H29 -> 0 | J29: =IF(AND(E29>=18,E29<=21), (Inputs!B16*(1+Inputs!B17)^(18-Inputs!B11))/4, 0) -> 0 | K29: =IF(AND(F29>=18,F29<=21), (Inputs!B16*(1+Inputs!B17)^(18-Inputs!B12))/4, 0) -> 0 | L29: =J29+K29 -> 0 | M29: =IF(E29=Inputs!B20, Inputs!B18*(1+Inputs!B19)^(Inputs!B20-Inputs!B11), 0) -> 0 | N29: =IF(F29=Inputs!B21, Inputs!B18*(1+Inputs!B19)^(Inputs!B21-Inputs!B12), 0) -> 0 | O29: =M29+N29 -> 0 | P29: =D29+I29+L29+O29 -> 3728320.6 | Q29: =(C29-P29)*IF(B29<Inputs!B5,Inputs!B9,Inputs!B10) -> -2037622.4 | R29: =(C29-P29)+Q29 -> -22413846
A30: =Inputs!B23 + ROW()-2 -> 2054 | B30: =Inputs!B3 + ROW()-2 -> 71 | C30: =IF(ROW()=2,Inputs!B6,R29) -> -22413846 | D30: =IF(B30<Inputs!B5,0, Inputs!B7*(1+Inputs!B8)^(B30-Inputs!B3)) -> 3989303 | E30: =Inputs!B11 + (B30-Inputs!B3) -> 41 | F30: =Inputs!B12 + (B30-Inputs!B3) -> 32 | G30: =IF(E30<18, Inputs!B13*(1+Inputs!B15)^(INT((B30-Inputs!B3)/Inputs!B22)), 0) -> 0 | H30: =IF(F30<18, Inputs!B14*(1+Inputs!B15)^(INT((B30-Inputs!B3)/Inputs!B22)), 0) -> 0 | I30: =G30+H30 -> 0 | J30: =IF(AND(E30>=18,E30<=21), (Inputs!B16*(1+Inputs!B17)^(18-Inputs!B11))/4, 0) -> 0 | K30: =IF(AND(F30>=18,F30<=21), (Inputs!B16*(1+Inputs!B17)^(18-Inputs!B12))/4, 0) -> 0 | L30: =J30+K30 -> 0 | M30: =IF(E30=Inputs!B20, Inputs!B18*(1+Inputs!B19)^(Inputs!B20-Inputs!B11), 0) -> 0 | N30: =IF(F30=Inputs!B21, Inputs!B18*(1+Inputs!B19)^(Inputs!B21-Inputs!B12), 0) -> 0 | O30: =M30+N30 -> 0 | P30: =D30+I30+L30+O30 -> 3989303 | Q30: =(C30-P30)*IF(B30<Inputs!B5,Inputs!B9,Inputs!B10) -> -2640314.9 | R30: =(C30-P30)+Q30 -> -29043464
A31: =Inputs!B23 + ROW()-2 -> 2055 | B31: =Inputs!B3 + ROW()-2 -> 72 | C31: =IF(ROW()=2,Inputs!B6,R30) -> -29043464 | D31: =IF(B31<Inputs!B5,0, Inputs!B7*(1+Inputs!B8)^(B31-Inputs!B3)) -> 4268554.2 | E31: =Inputs!B11 + (B31-Inputs!B3) -> 42 | F31: =Inputs!B12 + (B31-Inputs!B3) -> 33 | G31: =IF(E31<18, Inputs!B13*(1+Inputs!B15)^(INT((B31-Inputs!B3)/Inputs!B22)), 0) -> 0 | H31: =IF(F31<18, Inputs!B14*(1+Inputs!B15)^(INT((B31-Inputs!B3)/Inputs!B22)), 0) -> 0 | I31: =G31+H31 -> 0 | J31: =IF(AND(E31>=18,E31<=21), (Inputs!B16*(1+Inputs!B17)^(18-Inputs!B11))/4, 0) -> 0 | K31: =IF(AND(F31>=18,F31<=21), (Inputs!B16*(1+Inputs!B17)^(18-Inputs!B12))/4, 0) -> 0 | L31: =J31+K31 -> 0 | M31: =IF(E31=Inputs!B20, Inputs!B18*(1+Inputs!B19)^(Inputs!B20-Inputs!B11), 0) -> 0 | N31: =IF(F31=Inputs!B21, Inputs!B18*(1+Inputs!B19)^(Inputs!B21-Inputs!B12), 0) -> 0 | O31: =M31+N31 -> 0 | P31: =D31+I31+L31+O31 -> 4268554.2 | Q31: =(C31-P31)*IF(B31<Inputs!B5,Inputs!B9,Inputs!B10) -> -3331201.8 | R31: =(C31-P31)+Q31 -> -36643220
A32: =Inputs!B23 + ROW()-2 -> 2056 | B32: =Inputs!B3 + ROW()-2 -> 73 | C32: =IF(ROW()=2,Inputs!B6,R31) -> -36643220 | D32: =IF(B32<Inputs!B5,0, Inputs!B7*(1+Inputs!B8)^(B32-Inputs!B3)) -> 4567353 | E32: =Inputs!B11 + (B32-Inputs!B3) -> 43 | F32: =Inputs!B12 + (B32-Inputs!B3) -> 34 | G32: =IF(E32<18, Inputs!B13*(1+Inputs!B15)^(INT((B32-Inputs!B3)/Inputs!B22)), 0) -> 0 | H32: =IF(F32<18, Inputs!B14*(1+Inputs!B15)^(INT((B32-Inputs!B3)/Inputs!B22)), 0) -> 0 | I32: =G32+H32 -> 0 | J32: =IF(AND(E32>=18,E32<=21), (Inputs!B16*(1+Inputs!B17)^(18-Inputs!B11))/4, 0) -> 0 | K32: =IF(AND(F32>=18,F32<=21), (Inputs!B16*(1+Inputs!B17)^(18-Inputs!B12))/4, 0) -> 0 | L32: =J32+K32 -> 0 | M32: =IF(E32=Inputs!B20, Inputs!B18*(1+Inputs!B19)^(Inputs!B20-Inputs!B11), 0) -> 0 | N32: =IF(F32=Inputs!B21, Inputs!B18*(1+Inputs!B19)^(Inputs!B21-Inputs!B12), 0) -> 0 | O32: =M32+N32 -> 0 | P32: =D32+I32+L32+O32 -> 4567353 | Q32: =(C32-P32)*IF(B32<Inputs!B5,Inputs!B9,Inputs!B10) -> -4121057.3 | R32: =(C32-P32)+Q32 -> -45331631
A33: =Inputs!B23 + ROW()-2 -> 2057 | B33: =Inputs!B3 + ROW()-2 -> 74 | C33: =IF(ROW()=2,Inputs!B6,R32) -> -45331631 | D33: =IF(B33<Inputs!B5,0, Inputs!B7*(1+Inputs!B8)^(B33-Inputs!B3)) -> 4887067.7 | E33: =Inputs!B11 + (B33-Inputs!B3) -> 44 | F33: =Inputs!B12 + (B33-Inputs!B3) -> 35 | G33: =IF(E33<18, Inputs!B13*(1+Inputs!B15)^(INT((B33-Inputs!B3)/Inputs!B22)), 0) -> 0 | H33: =IF(F33<18, Inputs!B14*(1+Inputs!B15)^(INT((B33-Inputs!B3)/Inputs!B22)), 0) -> 0 | I33: =G33+H33 -> 0 | J33: =IF(AND(E33>=18,E33<=21), (Inputs!B16*(1+Inputs!B17)^(18-Inputs!B11))/4, 0) -> 0 | K33: =IF(AND(F33>=18,F33<=21), (Inputs!B16*(1+Inputs!B17)^(18-Inputs!B12))/4, 0) -> 0 | L33: =J33+K33 -> 0 | M33: =IF(E33=Inputs!B20, Inputs!B18*(1+Inputs!B19)^(Inputs!B20-Inputs!B11), 0) -> 0 | N33: =IF(F33=Inputs!B21, Inputs!B18*(1+Inputs!B19)^(Inputs!B21-Inputs!B12), 0) -> 0 | O33: =M33+N33 -> 0 | P33: =D33+I33+L33+O33 -> 4887067.7 | Q33: =(C33-P33)*IF(B33<Inputs!B5,Inputs!B9,Inputs!B10) -> -5021869.8 | R33: =(C33-P33)+Q33 -> -55240568
A34: =Inputs!B23 + ROW()-2 -> 2058 | B34: =Inputs!B3 + ROW()-2 -> 75 | C34: =IF(ROW()=2,Inputs!B6,R33) -> -55240568 | D34: =IF(B34<Inputs!B5,0, Inputs!B7*(1+Inputs!B8)^(B34-Inputs!B3)) -> 5229162.5 | E34: =Inputs!B11 + (B34-Inputs!B3) -> 45 | F34: =Inputs!B12 + (B34-Inputs!B3) -> 36 | G34: =IF(E34<18, Inputs!B13*(1+Inputs!B15)^(INT((B34-Inputs!B3)/Inputs!B22)), 0) -> 0 | H34: =IF(F34<18, Inputs!B14*(1+Inputs!B15)^(INT((B34-Inputs!B3)/Inputs!B22)), 0) -> 0 | I34: =G34+H34 -> 0 | J34: =IF(AND(E34>=18,E34<=21), (Inputs!B16*(1+Inputs!B17)^(18-Inputs!B11))/4, 0) -> 0 | K34: =IF(AND(F34>=18,F34<=21), (Inputs!B16*(1+Inputs!B17)^(18-Inputs!B12))/4, 0) -> 0 | L34: =J34+K34 -> 0 | M34: =IF(E34=Inputs!B20, Inputs!B18*(1+Inputs!B19)^(Inputs!B20-Inputs!B11), 0) -> 0 | N34: =IF(F34=Inputs!B21, Inputs!B18*(1+Inputs!B19)^(Inputs!B21-Inputs!B12), 0) -> 0 | O34: =M34+N34 -> 0 | P34: =D34+I34+L34+O34 -> 5229162.5 | Q34: =(C34-P34)*IF(B34<Inputs!B5,Inputs!B9,Inputs!B10) -> -6046973.1 | R34: =(C34-P34)+Q34 -> -66516704
A35: =Inputs!B23 + ROW()-2 -> 2059 | B35: =Inputs!B3 + ROW()-2 -> 76 | C35: =IF(ROW()=2,Inputs!B6,R34) -> -66516704 | D35: =IF(B35<Inputs!B5,0, Inputs!B7*(1+Inputs!B8)^(B35-Inputs!B3)) -> 5595203.9 | E35: =Inputs!B11 + (B35-Inputs!B3) -> 46 | F35: =Inputs!B12 + (B35-Inputs!B3) -> 37 | G35: =IF(E35<18, Inputs!B13*(1+Inputs!B15)^(INT((B35-Inputs!B3)/Inputs!B22)), 0) -> 0 | H35: =IF(F35<18, Inputs!B14*(1+Inputs!B15)^(INT((B35-Inputs!B3)/Inputs!B22)), 0) -> 0 | I35: =G35+H35 -> 0 | J35: =IF(AND(E35>=18,E35<=21), (Inputs!B16*(1+Inputs!B17)^(18-Inputs!B11))/4, 0) -> 0 | K35: =IF(AND(F35>=18,F35<=21), (Inputs!B16*(1+Inputs!B17)^(18-Inputs!B12))/4, 0) -> 0 | L35: =J35+K35 -> 0 | M35: =IF(E35=Inputs!B20, Inputs!B18*(1+Inputs!B19)^(Inputs!B20-Inputs!B11), 0) -> 0 | N35: =IF(F35=Inputs!B21, Inputs!B18*(1+Inputs!B19)^(Inputs!B21-Inputs!B12), 0) -> 0 | O35: =M35+N35 -> 0 | P35: =D35+I35+L35+O35 -> 5595203.9 | Q35: =(C35-P35)*IF(B35<Inputs!B5,Inputs!B9,Inputs!B10) -> -7211190.8 | R35: =(C35-P35)+Q35 -> -79323098
A36: =Inputs!B23 + ROW()-2 -> 2060 | B36: =Inputs!B3 + ROW()-2 -> 77 | C36: =IF(ROW()=2,Inputs!B6,R35) -> -79323098 | D36: =IF(B36<Inputs!B5,0, Inputs!B7*(1+Inputs!B8)^(B36-Inputs!B3)) -> 5986868.1 | E36: =Inputs!B11 + (B36-Inputs!B3) -> 47 | F36: =Inputs!B12 + (B36-Inputs!B3) -> 38 | G36: =IF(E36<18, Inputs!B13*(1+Inputs!B15)^(INT((B36-Inputs!B3)/Inputs!B22)), 0) -> 0 | H36: =IF(F36<18, Inputs!B14*(1+Inputs!B15)^(INT((B36-Inputs!B3)/Inputs!B22)), 0) -> 0 | I36: =G36+H36 -> 0 | J36: =IF(AND(E36>=18,E36<=21), (Inputs!B16*(1+Inputs!B17)^(18-Inputs!B11))/4, 0) -> 0 | K36: =IF(AND(F36>=18,F36<=21), (Inputs!B16*(1+Inputs!B17)^(18-Inputs!B12))/4, 0) -> 0 | L36: =J36+K36 -> 0 | M36: =IF(E36=Inputs!B20, Inputs!B18*(1+Inputs!B19)^(Inputs!B20-Inputs!B11), 0) -> 0 | N36: =IF(F36=Inputs!B21, Inputs!B18*(1+Inputs!B19)^(Inputs!B21-Inputs!B12), 0) -> 0 | O36: =M36+N36 -> 0 | P36: =D36+I36+L36+O36 -> 5986868.1 | Q36: =(C36-P36)*IF(B36<Inputs!B5,Inputs!B9,Inputs!B10) -> -8530996.6 | R36: =(C36-P36)+Q36 -> -93840963
A37: =Inputs!B23 + ROW()-2 -> 2061 | B37: =Inputs!B3 + ROW()-2 -> 78 | C37: =IF(ROW()=2,Inputs!B6,R36) -> -93840963 | D37: =IF(B37<Inputs!B5,0, Inputs!B7*(1+Inputs!B8)^(B37-Inputs!B3)) -> 6405948.9 | E37: =Inputs!B11 + (B37-Inputs!B3) -> 48 | F37: =Inputs!B12 + (B37-Inputs!B3) -> 39 | G37: =IF(E37<18, Inputs!B13*(1+Inputs!B15)^(INT((B37-Inputs!B3)/Inputs!B22)), 0) -> 0 | H37: =IF(F37<18, Inputs!B14*(1+Inputs!B15)^(INT((B37-Inputs!B3)/Inputs!B22)), 0) -> 0 | I37: =G37+H37 -> 0 | J37: =IF(AND(E37>=18,E37<=21), (Inputs!B16*(1+Inputs!B17)^(18-Inputs!B11))/4, 0) -> 0 | K37: =IF(AND(F37>=18,F37<=21), (Inputs!B16*(1+Inputs!B17)^(18-Inputs!B12))/4, 0) -> 0 | L37: =J37+K37 -> 0 | M37: =IF(E37=Inputs!B20, Inputs!B18*(1+Inputs!B19)^(Inputs!B20-Inputs!B11), 0) -> 0 | N37: =IF(F37=Inputs!B21, Inputs!B18*(1+Inputs!B19)^(Inputs!B21-Inputs!B12), 0) -> 0 | O37: =M37+N37 -> 0 | P37: =D37+I37+L37+O37 -> 6405948.9 | Q37: =(C37-P37)*IF(B37<Inputs!B5,Inputs!B9,Inputs!B10) -> -10024691 | R37: =(C37-P37)+Q37 -> -1.102716e+08
A38: =Inputs!B23 + ROW()-2 -> 2062 | B38: =Inputs!B3 + ROW()-2 -> 79 | C38: =IF(ROW()=2,Inputs!B6,R37) -> -1.102716e+08 | D38: =IF(B38<Inputs!B5,0, Inputs!B7*(1+Inputs!B8)^(B38-Inputs!B3)) -> 6854365.3 | E38: =Inputs!B11 + (B38-Inputs!B3) -> 49 | F38: =Inputs!B12 + (B38-Inputs!B3) -> 40 | G38: =IF(E38<18, Inputs!B13*(1+Inputs!B15)^(INT((B38-Inputs!B3)/Inputs!B22)), 0) -> 0 | H38: =IF(F38<18, Inputs!B14*(1+Inputs!B15)^(INT((B38-Inputs!B3)/Inputs!B22)), 0) -> 0 | I38: =G38+H38 -> 0 | J38: =IF(AND(E38>=18,E38<=21), (Inputs!B16*(1+Inputs!B17)^(18-Inputs!B11))/4, 0) -> 0 | K38: =IF(AND(F38>=18,F38<=21), (Inputs!B16*(1+Inputs!B17)^(18-Inputs!B12))/4, 0) -> 0 | L38: =J38+K38 -> 0 | M38: =IF(E38=Inputs!B20, Inputs!B18*(1+Inputs!B19)^(Inputs!B20-Inputs!B11), 0) -> 0 | N38: =IF(F38=Inputs!B21, Inputs!B18*(1+Inputs!B19)^(Inputs!B21-Inputs!B12), 0) -> 0 | O38: =M38+N38 -> 0 | P38: =D38+I38+L38+O38 -> 6854365.3 | Q38: =(C38-P38)*IF(B38<Inputs!B5,Inputs!B9,Inputs!B10) -> -11712597 | R38: =(C38-P38)+Q38 -> -1.2883857e+08
A39: =Inputs!B23 + ROW()-2 -> 2063 | B39: =Inputs!B3 + ROW()-2 -> 80 | C39: =IF(ROW()=2,Inputs!B6,R38) -> -1.2883857e+08 | D39: =IF(B39<Inputs!B5,0, Inputs!B7*(1+Inputs!B8)^(B39-Inputs!B3)) -> 7334170.9 | E39: =Inputs!B11 + (B39-Inputs!B3) -> 50 | F39: =Inputs!B12 + (B39-Inputs!B3) -> 41 | G39: =IF(E39<18, Inputs!B13*(1+Inputs!B15)^(INT((B39-Inputs!B3)/Inputs!B22)), 0) -> 0 | H39: =IF(F39<18, Inputs!B14*(1+Inputs!B15)^(INT((B39-Inputs!B3)/Inputs!B22)), 0) -> 0 | I39: =G39+H39 -> 0 | J39: =IF(AND(E39>=18,E39<=21), (Inputs!B16*(1+Inputs!B17)^(18-Inputs!B11))/4, 0) -> 0 | K39: =IF(AND(F39>=18,F39<=21), (Inputs!B16*(1+Inputs!B17)^(18-Inputs!B12))/4, 0) -> 0 | L39: =J39+K39 -> 0 | M39: =IF(E39=Inputs!B20, Inputs!B18*(1+Inputs!B19)^(Inputs!B20-Inputs!B11), 0) -> 0 | N39: =IF(F39=Inputs!B21, Inputs!B18*(1+Inputs!B19)^(Inputs!B21-Inputs!B12), 0) -> 0 | O39: =M39+N39 -> 0 | P39: =D39+I39+L39+O39 -> 7334170.9 | Q39: =(C39-P39)*IF(B39<Inputs!B5,Inputs!B9,Inputs!B10) -> -13617274 | R39: =(C39-P39)+Q39 -> -1.4979001e+08
A40: =Inputs!B23 + ROW()-2 -> 2064 | B40: =Inputs!B3 + ROW()-2 -> 81 | C40: =IF(ROW()=2,Inputs!B6,R39) -> -1.4979001e+08 | D40: =IF(B40<Inputs!B5,0, Inputs!B7*(1+Inputs!B8)^(B40-Inputs!B3)) -> 7847562.8 | E40: =Inputs!B11 + (B40-Inputs!B3) -> 51 | F40: =Inputs!B12 + (B40-Inputs!B3) -> 42 | G40: =IF(E40<18, Inputs!B13*(1+Inputs!B15)^(INT((B40-Inputs!B3)/Inputs!B22)), 0) -> 0 | H40: =IF(F40<18, Inputs!B14*(1+Inputs!B15)^(INT((B40-Inputs!B3)/Inputs!B22)), 0) -> 0 | I40: =G40+H40 -> 0 | J40: =IF(AND(E40>=18,E40<=21), (Inputs!B16*(1+Inputs!B17)^(18-Inputs!B11))/4, 0) -> 0 | K40: =IF(AND(F40>=18,F40<=21), (Inputs!B16*(1+Inputs!B17)^(18-Inputs!B12))/4, 0) -> 0 | L40: =J40+K40 -> 0 | M40: =IF(E40=Inputs!B20, Inputs!B18*(1+Inputs!B19)^(Inputs!B20-Inputs!B11), 0) -> 0 | N40: =IF(F40=Inputs!B21, Inputs!B18*(1+Inputs!B19)^(Inputs!B21-Inputs!B12), 0) -> 0 | O40: =M40+N40 -> 0 | P40: =D40+I40+L40+O40 -> 7847562.8 | Q40: =(C40-P40)*IF(B40<Inputs!B5,Inputs!B9,Inputs!B10) -> -15763757 | R40: =(C40-P40)+Q40 -> -173401330
